drf_versioned_models/__init__.py
drf_versioned_models/apps.py
drf_versioned_models/models.py
drf_versioned_models/routers.py
drf_versioned_models/serializers.py
drf_versioned_models/viewsets.py
drf_versioned_models-0.1.0.dist-info/LICENSE
drf_versioned_models-0.1.0.dist-info/METADATA
drf_versioned_models-0.1.0.dist-info/WHEEL
drf_versioned_models-0.1.0.dist-info/top_level.txt
drf_versioned_models-0.1.0.dist-info/RECORD
