Metadata-Version: 2.1
Name: drf-versioned-models
Version: 0.1.0
Summary: Versioned models support for Django REST Framework
Author-email: "QuantTide Inc." <opensource@quanttide.com>
License: BSD 3-Clause License
Classifier: Programming Language :: Python :: 3
Classifier: Framework :: Django
Requires-Python: >=3
License-File: LICENSE
Requires-Dist: django (>=3.0)
Requires-Dist: djangorestframework (>=3.0)
Requires-Dist: drf-nested-routers
